yatiml/__init__.py
yatiml/constructors.py
yatiml/dumper.py
yatiml/exceptions.py
yatiml/helpers.py
yatiml/introspection.py
yatiml/irecognizer.py
yatiml/loader.py
yatiml/py.typed
yatiml/recognizer.py
yatiml/representers.py
yatiml/util.py
yatiml-0.11.1.dist-info/LICENSE
yatiml-0.11.1.dist-info/METADATA
yatiml-0.11.1.dist-info/NOTICE
yatiml-0.11.1.dist-info/WHEEL
yatiml-0.11.1.dist-info/top_level.txt
yatiml-0.11.1.dist-info/RECORD
