Metadata-Version: 2.1
Name: yatiml
Version: 0.11.1
Summary: Reading, checking and writing YAML from Python
Home-page: https://github.com/yatiml/yatiml
Author: Lourens Veen
Author-email: l.veen@esciencecenter.nl
License: Apache Software License 2.0
Keywords: yatiml
Classifier: Development Status :: 4 - Beta
Classifier: Intended Audience :: Developers
Classifier: License :: OSI Approved :: Apache Software License
Classifier: Natural Language :: English
Classifier: Programming Language :: Python :: 3
Classifier: Programming Language :: Python :: 3.7
Classifier: Programming Language :: Python :: 3.8
Classifier: Programming Language :: Python :: 3.9
Classifier: Programming Language :: Python :: 3.10
Classifier: Programming Language :: Python :: 3.11
Classifier: Programming Language :: Python :: 3.12
License-File: LICENSE
License-File: NOTICE
Requires-Dist: PyYAML!=5.4.1,>=5.1
Requires-Dist: typing_extensions
